tourbillon_linux-0.4.1-py3.4-nspkg.pth
tourbillon/linux/__init__.py
tourbillon/linux/linux/__init__.py
tourbillon/linux/linux/linux.py
tourbillon/linux/linux2/__init__.py
tourbillon/linux/linux2/linux.py
tourbillon_linux-0.4.1.dist-info/DESCRIPTION.rst
tourbillon_linux-0.4.1.dist-info/METADATA
tourbillon_linux-0.4.1.dist-info/RECORD
tourbillon_linux-0.4.1.dist-info/WHEEL
tourbillon_linux-0.4.1.dist-info/metadata.json
tourbillon_linux-0.4.1.dist-info/namespace_packages.txt
tourbillon_linux-0.4.1.dist-info/top_level.txt
