Metadata-Version: 2.0
Name: tourbillon-linux
Version: 0.4.1
Summary: A tourbillon plugin for collecting metrics from linux.
Home-page: https://github.com/tourbillonpy/tourbillon-linux
Author: The Tourbillon Team
Author-email: tourbillonpy@gmail.com
License: ASF
Keywords: monitoring metrics agent influxdb linux
Platform: UNKNOWN
Classifier: Development Status :: 4 - Beta
Classifier: Intended Audience :: Developers
Classifier: Intended Audience :: System Administrators
Classifier: License :: OSI Approved :: Apache Software License
Classifier: Operating System :: POSIX :: Linux
Classifier: Programming Language :: Python
Classifier: Programming Language :: Python :: 2.7
Classifier: Programming Language :: Python :: 3.4
Classifier: Programming Language :: Python :: 3.5
Classifier: Topic :: System :: Monitoring
Requires-Dist: psutil (==3.1.1)
